yaqd_picotech/VERSION
yaqd_picotech/__init__.py
yaqd_picotech/__version__.py
yaqd_picotech/_picotech_adc_triggered.py
yaqd_picotech/_picotech_adc_triggered_gui.py
yaqd_picotech/picotech-adc-triggered.avpr
yaqd_picotech/picotech-adc-triggered.toml
yaqd_picotech-2022.4.0.dist-info/entry_points.txt
yaqd_picotech-2022.4.0.dist-info/LICENSE
yaqd_picotech-2022.4.0.dist-info/WHEEL
yaqd_picotech-2022.4.0.dist-info/METADATA
yaqd_picotech-2022.4.0.dist-info/RECORD
