Metadata-Version: 2.1
Name: yaqd-picotech
Version: 2022.4.0
Summary: yaq Daemon for Picotech oscilloscopes under triggered operation.
Home-page: https://yaq.fyi
Author: Dan Kohler
Author-email: ddkohler@wisc.edu
Requires-Python: >=3.7
Classifier: Development Status :: 2 - Pre-Alpha
Classifier: Intended Audience :: Science/Research
Classifier: License :: OSI Approved :: ISC License (ISCL)
Classifier: Natural Language :: English
Classifier: Programming Language :: Python :: 3
Classifier: Programming Language :: Python :: 3.7
Classifier: Programming Language :: Python :: 3.8
Classifier: Topic :: Scientific/Engineering
Requires-Dist: yaqd-core>=2020.12.0
Requires-Dist: picosdk>=1.0
Requires-Dist: black ; extra == "dev"
Requires-Dist: pre-commit ; extra == "dev"
Project-URL: Issues, https://gitlab.com/yaq/yaqd-picotech/issues
Project-URL: Source, https://gitlab.com/yaq/yaqd-picotech
Provides-Extra: dev
